pyBKTR/__init__.py
pyBKTR/_likelihood_evaluator.py
pyBKTR/_result_logger.py
pyBKTR/_samplers.py
pyBKTR/bktr.py
pyBKTR/distances.py
pyBKTR/kernels.py
pyBKTR/plots.py
pyBKTR/tensor_ops.py
pyBKTR/utils.py
pyBKTR/data/__init__.py
pyBKTR/data/bixi_spatial_features.csv
pyBKTR/data/bixi_spatial_locations.csv
pyBKTR/data/bixi_station_departures.csv
pyBKTR/data/bixi_temporal_features.csv
pyBKTR/data/bixi_temporal_locations.csv
pyBKTR/data/raw_data/__init__.py
pyBKTR/data/raw_data/_bixi_cleanup.py
pyBKTR/examples/__init__.py
pyBKTR/examples/bixi.py
pyBKTR-0.2.0.dist-info/LICENSE
pyBKTR-0.2.0.dist-info/METADATA
pyBKTR-0.2.0.dist-info/WHEEL
pyBKTR-0.2.0.dist-info/top_level.txt
pyBKTR-0.2.0.dist-info/RECORD
