Metadata-Version: 2.1
Name: pyBKTR
Version: 0.2.0
Summary: Python implementation of the Scalable Spatiotemporally Varying Coefficient Modelling with Bayesian Kernelized Tensor Regression
Author: Mengying Lei, Aurelie Labbe, Lijun Sun
Author-email: Julien Lanthier <julien.lanthier@hec.ca>
Project-URL: Homepage, https://github.com/julien-hec/pyBKTR
Project-URL: Bug Tracker, https://github.com/julien-hec/pyBKTR/issues
Classifier: Development Status :: 1 - Planning
Classifier: Intended Audience :: Science/Research
Classifier: Programming Language :: Python :: 3
Classifier: Programming Language :: Python :: 3.10
Requires-Python: <4,>=3.10
License-File: LICENSE
Requires-Dist: torch >=1.12.1
Requires-Dist: numpy >=1.22.3
Requires-Dist: pandas >=1.4.2
Requires-Dist: plotly >=5.10.0
Requires-Dist: formulaic >=0.5.2
Provides-Extra: dev
Requires-Dist: black ==22.6.0 ; extra == 'dev'
Requires-Dist: flake8 ==4.0.1 ; extra == 'dev'
Requires-Dist: pre-commit ==2.20.0 ; extra == 'dev'
Requires-Dist: Sphinx ==6.1.3 ; extra == 'dev'
Requires-Dist: sphinx-rtd-theme ==1.2.0 ; extra == 'dev'
Requires-Dist: nbsphinx ==0.8.12 ; extra == 'dev'
Requires-Dist: kaleido ==0.2.1 ; extra == 'dev'
